src/__init__.py
src/breadcrumbs.py
src/core.py
src/custom.py
src/helper.py
src/imageviewer.py
src/model.py
src/navcopier.py
src/navgator.py
src/navwatcher.py
src/panes.py
src/pub.py
src/settings.py
src/tabs.py
navgator-0.5.2.dist-info/LICENSE
navgator-0.5.2.dist-info/METADATA
navgator-0.5.2.dist-info/WHEEL
navgator-0.5.2.dist-info/entry_points.txt
navgator-0.5.2.dist-info/top_level.txt
navgator-0.5.2.dist-info/RECORD
