Metadata-Version: 2.1
Name: navgator
Version: 0.5.2
Summary: A multi-paned multi-tabbed file manager
Home-page: https://github.com/naveed-patel/navgator
Author: Naveed Patel
Author-email: 20777764+naveed-patel@users.noreply.github.com
License: MIT
Platform: UNKNOWN
Classifier: License :: OSI Approved :: MIT License
Classifier: Programming Language :: Python
Classifier: Programming Language :: Python :: 3
Classifier: Programming Language :: Python :: 3.7
Classifier: Programming Language :: Python :: Implementation :: CPython
Classifier: Programming Language :: Python :: Implementation :: PyPy
Classifier: Topic :: Desktop Environment :: File Managers
Requires-Python: >=3.7.0
Requires-Dist: PyQt5
Requires-Dist: watchdog
Requires-Dist: send2trash
Requires-Dist: pillow
Requires-Dist: psutil
Requires-Dist: file-magic
